setup.py
structured_log.egg-info/PKG-INFO
structured_log.egg-info/SOURCES.txt
structured_log.egg-info/dependency_links.txt
structured_log.egg-info/not-zip-safe
structured_log.egg-info/requires.txt
structured_log.egg-info/top_level.txt
structured_logging/__init__.py
structured_logging/logging.py
structured_logging/structured_logging.pyd