Metadata-Version: 2.1
Name: structured-log
Version: 1.12
Summary: Structured logging
Author: Alex Yung
